mpv_history_daemon/__init__.py
mpv_history_daemon/__main__.py
mpv_history_daemon/daemon.py
mpv_history_daemon/events.py
mpv_history_daemon/merge.py
mpv_history_daemon/py.typed
mpv_history_daemon/serialize.py
mpv_history_daemon/utils.py
mpv_history_daemon-0.2.6.data/scripts/mpv_history_daemon_restart
mpv_history_daemon-0.2.6.dist-info/LICENSE
mpv_history_daemon-0.2.6.dist-info/METADATA
mpv_history_daemon-0.2.6.dist-info/WHEEL
mpv_history_daemon-0.2.6.dist-info/entry_points.txt
mpv_history_daemon-0.2.6.dist-info/top_level.txt
mpv_history_daemon-0.2.6.dist-info/RECORD
