Metadata-Version: 2.1
Name: mpv_history_daemon
Version: 0.2.6
Summary: Daemon which connects to active mpv instances, saving a history of what I watch/listen to
Home-page: https://github.com/seanbreckenridge/mpv_history_daemon
Author: Sean Breckenridge
Author-email: "seanbrecke@gmail.com"
License: MIT
Classifier: Development Status :: 3 - Alpha
Classifier: Intended Audience :: End Users/Desktop
Classifier: License :: OSI Approved :: MIT License
Classifier: Natural Language :: English
Classifier: Programming Language :: Python :: 3
Classifier: Programming Language :: Python :: 3 :: Only
Classifier: Programming Language :: Python :: 3.8
Classifier: Programming Language :: Python :: 3.9
Classifier: Programming Language :: Python :: 3.10
Classifier: Programming Language :: Python :: 3.11
Classifier: Programming Language :: Python :: 3.12
Requires-Python: >=3.8
License-File: LICENSE
Requires-Dist: click >=8.1
Requires-Dist: logzero
Requires-Dist: python-mpv-jsonipc
Requires-Dist: simplejson
Requires-Dist: kompress
Provides-Extra: optional
Requires-Dist: orjson ; extra == 'optional'
Provides-Extra: testing
Requires-Dist: flake8 ; extra == 'testing'
Requires-Dist: mypy ; extra == 'testing'
